{"csp":"persistmgr","parms":[{"name":"PersistAsName","requires":{"osx":"","osxEnd":"","mx":"4.1","api":"","osxSpecific":"","osxSpecificList":"","osxExclude":"","osxExcludeEnd":""}},{"name":"PersistAsOrder","requires":{"osx":"","osxEnd":"","mx":"4.2","api":"","osxSpecific":"","osxSpecificList":"","osxExclude":"","osxExcludeEnd":""}},{"name":"PersistAsVersion","requires":{"osx":"","osxEnd":"","mx":"4.2","api":"","osxSpecific":"","osxSpecificList":"","osxExclude":"","osxExcludeEnd":""}},{"listitems":[{"code":true,"name":true,"requires":{"osx":"","osxEnd":"","mx":"4.2","api":"","osxSpecific":"","osxSpecificList":"","osxExclude":"","osxExcludeEnd":""}},{"code":false,"name":false,"requires":{"osx":"","osxEnd":"","mx":"4.2","api":"","osxSpecific":"","osxSpecificList":"","osxExclude":"","osxExcludeEnd":""}}],"name":"PersistIfError"},{"listitems":[{"code":1,"name":"Add current XML as a persistent profile","requires":{"osx":"","osxEnd":"","mx":"4.1","api":"","osxSpecific":"","osxSpecificList":"","osxExclude":"","osxExcludeEnd":""}},{"code":2,"name":"Remove the specified persistent profile","requires":{"osx":"","osxEnd":"","mx":"4.1","api":"","osxSpecific":"","osxSpecificList":"","osxExclude":"","osxExcludeEnd":""}},{"code":3,"name":"Enable the specified persistent profile","requires":{"osx":"","osxEnd":"","mx":"4.2","api":"","osxSpecific":"","osxSpecificList":"","osxExclude":"","osxExcludeEnd":""}},{"code":4,"name":"Disable the specified persistent profile","requires":{"osx":"","osxEnd":"","mx":"4.2","api":"","osxSpecific":"","osxSpecificList":"","osxExclude":"","osxExcludeEnd":""}}],"name":"PersistAction"}]}